{
  "data": [
    {
        "item": "Learn how the government can become your customer!",
        "count": "7"
    },
    {
        "item": "Part of a series of BID roundtables exploring diversity, equity, and inclusion in the NYC BID network; facilitated by SBS",
        "count": "4"
    },
    {
        "item": "Legal Essentials for Doing Business Online",
        "count": "3"
    },
    {
        "item": "The New York City Department of Small Business Services will be hosting a certification workshop",
        "count": "3"
    },
    {
        "item": "Email Marketing",
        "count": "3"
    },
    {
        "item": "Building an Operational Plan",
        "count": "3"
    },
    {
        "item": "Business Finances 1",
        "count": "2"
    },
    {
        "item": "WEBINAR | QuickBooks, BROOKLYN, 10/15/2020",
        "count": "2"
    },
    {
        "item": "Join this webinar to learn about State requirements, recommendations, and resources available to help Phase I businesses reopen in NYC.",
        "count": "2"
    },
    {
        "item": "Choosing the Right Business Structure",
        "count": "2"
    },
    {
        "item": "Signing A Commercial Lease",
        "count": "2"
    },
    {
        "item": "Test Summary",
        "count": "2"
    },
    {
        "item": "Join this webinar to learn about State requirements, recommendations and resources available to help Phase I, II, III businesses to reopen.",
        "count": "2"
    },
    {
        "item": "Social Media Marketing",
        "count": "2"
    },
    {
        "item": "Creating a Business Idea that Works",
        "count": "2"
    },
    {
        "item": "Building Your Own Business Website",
        "count": "2"
    },
    {
        "item": "Our webinar covers state requirements, recommendations, and resources available to help Phases 1-4 businesses to to reopen in NYC.",
        "count": "1"
    },
    {
        "item": "Peer-led, flexible discussion among BID staff about membership registration and database management",
        "count": "1"
    },
    {
        "item": "Elegir la estructura legal correcta",
        "count": "1"
    }
]
}